django_triflesoft_pages-0.4.1601022010.dist-info/DESCRIPTION.rst
django_triflesoft_pages-0.4.1601022010.dist-info/METADATA
django_triflesoft_pages-0.4.1601022010.dist-info/RECORD
django_triflesoft_pages-0.4.1601022010.dist-info/WHEEL
django_triflesoft_pages-0.4.1601022010.dist-info/metadata.json
django_triflesoft_pages-0.4.1601022010.dist-info/top_level.txt
pages/__init__.py
pages/admin.py
pages/models.py
pages/urls.py
pages/views.py
